test_poetry_vp/__init__.py
test_poetry_vp/api/__init__.py
test_poetry_vp/api/apex/__init__.py
test_poetry_vp/api/apex/fiddef.py
test_poetry_vp/api/apex/FixApi.dll
test_poetry_vp/api/apex/vnapex.py
test_poetry_vp/api/ctp/__init__.py
test_poetry_vp/api/da/__init__.py
test_poetry_vp/api/femas/__init__.py
test_poetry_vp/api/hft/__init__.py
test_poetry_vp/api/hft/generator/generate_api_functions.py
test_poetry_vp/api/hft/generator/generate_struct.py
test_poetry_vp/api/hft/generator/hft_constant.py
test_poetry_vp/api/hft/generator/hft_struct.py
test_poetry_vp/api/hft/generator/hft_typedef.py
test_poetry_vp/api/hft/hft_constant.py
test_poetry_vp/api/hft/include/hft/header_for_generator/hft_trader_api_.h
test_poetry_vp/api/hft/include/hft/header_for_generator/hft_trader_struct_.h
test_poetry_vp/api/hft/include/hft/hft_option_trader_api.h
test_poetry_vp/api/hft/include/hft/hft_trader_api.h
test_poetry_vp/api/hft/include/hft/hft_trader_common.h
test_poetry_vp/api/hft/include/hft/hft_trader_error.h
test_poetry_vp/api/hft/include/hft/hft_trader_struct.h
test_poetry_vp/api/hft/include/pybind11/attr.h
test_poetry_vp/api/hft/include/pybind11/buffer_info.h
test_poetry_vp/api/hft/include/pybind11/cast.h
test_poetry_vp/api/hft/include/pybind11/chrono.h
test_poetry_vp/api/hft/include/pybind11/common.h
test_poetry_vp/api/hft/include/pybind11/complex.h
test_poetry_vp/api/hft/include/pybind11/detail/class.h
test_poetry_vp/api/hft/include/pybind11/detail/common.h
test_poetry_vp/api/hft/include/pybind11/detail/descr.h
test_poetry_vp/api/hft/include/pybind11/detail/init.h
test_poetry_vp/api/hft/include/pybind11/detail/internals.h
test_poetry_vp/api/hft/include/pybind11/detail/typeid.h
test_poetry_vp/api/hft/include/pybind11/eigen.h
test_poetry_vp/api/hft/include/pybind11/embed.h
test_poetry_vp/api/hft/include/pybind11/eval.h
test_poetry_vp/api/hft/include/pybind11/functional.h
test_poetry_vp/api/hft/include/pybind11/iostream.h
test_poetry_vp/api/hft/include/pybind11/numpy.h
test_poetry_vp-0.1.1.dist-info/LICENSE
test_poetry_vp-0.1.1.dist-info/WHEEL
test_poetry_vp-0.1.1.dist-info/METADATA
test_poetry_vp-0.1.1.dist-info/RECORD
