Metadata-Version: 2.1
Name: test-poetry-vp
Version: 0.1.1
Summary: test for poetry
Author: Your Name
Author-email: you@example.com
Requires-Python: >=3.10,<3.11
Classifier: Programming Language :: Python :: 3
Classifier: Programming Language :: Python :: 3.10
Requires-Dist: PyQt5 (>=5.15.6,<6.0.0)
Requires-Dist: QDarkStyle (>=3.0.3,<4.0.0)
Requires-Dist: QScintilla (>=2.13.1,<3.0.0)
Requires-Dist: WMI (>=1.5.1,<2.0.0)
Requires-Dist: exchange-calendars (>=3.5,<4.0)
Requires-Dist: matplotlib (>=3.5.1,<4.0.0)
Requires-Dist: numpy (>=1.21.5,<2.0.0)
Requires-Dist: pandas (>=1.3.5,<2.0.0)
Requires-Dist: plotly (>=5.4.0,<6.0.0)
Requires-Dist: psycopg2-binary (>=2.9.2,<3.0.0)
Requires-Dist: pycryptodome (>=3.12.0,<4.0.0)
Requires-Dist: pyqtgraph (>=0.12.3,<0.13.0)
Requires-Dist: pyzmq (>=22.3.0,<23.0.0)
Requires-Dist: six (>=1.16.0,<2.0.0)
Requires-Dist: tzlocal (>=4.1,<5.0)
Requires-Dist: vnpy-algotrading (>=1.0.1,<2.0.0)
Requires-Dist: vnpy-chartwizard (>=1.0.1,<2.0.0)
Requires-Dist: vnpy-ctabacktester (>=1.0.3,<2.0.0)
Requires-Dist: vnpy-ctastrategy (>=1.0.6,<2.0.0)
Requires-Dist: vnpy-ctp (>=6.5.1,<7.0.0)
Requires-Dist: vnpy-ctptest (>=6.5.1,<7.0.0)
Requires-Dist: vnpy-da (>=1.12.0,<2.0.0)
Requires-Dist: vnpy-datamanager (>=1.0.4,<2.0.0)
Requires-Dist: vnpy-datarecorder (>=1.0.2,<2.0.0)
Requires-Dist: vnpy-esunny (>=1.0.2,<2.0.0)
Requires-Dist: vnpy-femas (>=1.0.0,<2.0.0)
Requires-Dist: vnpy-ib (>=9.81.1,<10.0.0)
Requires-Dist: vnpy-mini (>=1.5.6,<2.0.0)
Requires-Dist: vnpy-optionmaster (>=1.0.1,<2.0.0)
Requires-Dist: vnpy-ost (>=2.0.1,<3.0.0)
Requires-Dist: vnpy-paperaccount (>=1.0.0,<2.0.0)
Requires-Dist: vnpy-portfoliomanager (>=1.0.0,<2.0.0)
Requires-Dist: vnpy-portfoliostrategy (>=1.0.0,<2.0.0)
Requires-Dist: vnpy-rest (>=1.0.3,<2.0.0)
Requires-Dist: vnpy-riskmanager (>=1.0.2,<2.0.0)
Requires-Dist: vnpy-rohon (>=6.5.1,<7.0.0)
Requires-Dist: vnpy-scripttrader (>=1.0.0,<2.0.0)
Requires-Dist: vnpy-sgit (>=4.8.2,<5.0.0)
Requires-Dist: vnpy-sopt (>=3.5.5,<4.0.0)
Requires-Dist: vnpy-spreadtrading (>=1.1.3,<2.0.0)
Requires-Dist: vnpy-sqlite (>=1.0.0,<2.0.0)
Requires-Dist: vnpy-tap (>=9.0.0,<10.0.0)
Requires-Dist: vnpy-tora (>=2021.12.5,<2022.0.0)
Requires-Dist: vnpy-tts (>=6.5.1,<7.0.0)
Requires-Dist: vnpy-uft (>=3.7.2,<4.0.0)
Requires-Dist: vnpy-websocket (>=1.0.2,<2.0.0)
Requires-Dist: vnpy-webtrader (>=1.0.2,<2.0.0)
Requires-Dist: vnpy-xtp (>=2.2.27,<3.0.0)
Requires-Dist: wheel (>=0.37.0,<0.38.0)
